nnpdf_data/__init__.py
nnpdf_data/_version.py
nnpdf_data/commondata/ATHENA_NC_105GEV_EP/data.yaml
nnpdf_data/commondata/ATHENA_NC_105GEV_EP/kinematics.yaml
nnpdf_data/commondata/ATHENA_NC_105GEV_EP/metadata.yaml
nnpdf_data/commondata/ATHENA_NC_105GEV_EP/uncertainties.yaml
nnpdf_data/commondata/ATHENA_NC_140GEV_EP/data.yaml
nnpdf_data/commondata/ATHENA_NC_140GEV_EP/kinematics.yaml
nnpdf_data/commondata/ATHENA_NC_140GEV_EP/metadata.yaml
nnpdf_data/commondata/ATHENA_NC_140GEV_EP/uncertainties.yaml
nnpdf_data/commondata/ATHENA_NC_29GEV_EP/data.yaml
nnpdf_data/commondata/ATHENA_NC_29GEV_EP/kinematics.yaml
nnpdf_data/commondata/ATHENA_NC_29GEV_EP/metadata.yaml
nnpdf_data/commondata/ATHENA_NC_29GEV_EP/uncertainties.yaml
nnpdf_data/commondata/ATHENA_NC_45GEV_EP/data.yaml
nnpdf_data/commondata/ATHENA_NC_45GEV_EP/kinematics.yaml
nnpdf_data/commondata/ATHENA_NC_45GEV_EP/metadata.yaml
nnpdf_data/commondata/ATHENA_NC_45GEV_EP/uncertainties.yaml
nnpdf_data/commondata/ATHENA_NC_63GEV_EP/data.yaml
nnpdf_data/commondata/ATHENA_NC_63GEV_EP/kinematics.yaml
nnpdf_data/commondata/ATHENA_NC_63GEV_EP/metadata.yaml
nnpdf_data/commondata/ATHENA_NC_63GEV_EP/uncertainties.yaml
nnpdf_data/commondata/ATLAS_1JET_13TEV_DIF/data.yaml
nnpdf_data/commondata/ATLAS_1JET_13TEV_DIF/data_altcorr1.yaml
nnpdf_data/commondata/ATLAS_1JET_13TEV_DIF/kinematics.yaml
nnpdf_data/commondata/ATLAS_1JET_13TEV_DIF/kinematics_altcorr1.yaml
nnpdf_data/commondata/ATLAS_1JET_13TEV_DIF/metadata.yaml
nnpdf_data/commondata/ATLAS_1JET_13TEV_DIF/uncertainties_altcorr1_lumi.yaml
nnpdf_data/commondata/ATLAS_1JET_13TEV_DIF/uncertainties_altcorr1_wo-lumi.yaml
nnpdf_data/commondata/ATLAS_1JET_13TEV_DIF/uncertainties_lumi.yaml
nnpdf_data/commondata/ATLAS_1JET_13TEV_DIF/uncertainties_wo-lumi.yaml
nnpdf_data/commondata/ATLAS_1JET_8TEV_R06/data.yaml
nnpdf_data/commondata/ATLAS_1JET_8TEV_R06/kinematics.yaml
nnpdf_data/commondata/ATLAS_1JET_8TEV_R06/metadata.yaml
nnpdf_data/commondata/ATLAS_1JET_8TEV_R06/uncertainties.yaml
nnpdf_data-4.1.1.dist-info/METADATA
nnpdf_data-4.1.1.dist-info/WHEEL
nnpdf_data-4.1.1.dist-info/RECORD
