Metadata-Version: 2.4
Name: nnpdf_data
Version: 4.1.1
Summary: The NNPDF data repository
License: GPL-3.0-or-later
Author: NNPDF Collaboration
Requires-Python: >=3.9,<4.0
Classifier: License :: OSI Approved :: GNU General Public License v3 (GPLv3)
Classifier: License :: OSI Approved :: GNU General Public License v3 or later (GPLv3+)
Classifier: Programming Language :: Python
Classifier: Programming Language :: Python :: 3
Classifier: Programming Language :: Python :: 3.9
Classifier: Programming Language :: Python :: 3.10
Classifier: Programming Language :: Python :: 3.11
Classifier: Programming Language :: Python :: 3.12
Classifier: Programming Language :: Python :: 3.13
Classifier: Programming Language :: Python :: 3.14
Classifier: Topic :: Scientific/Engineering
Classifier: Topic :: Scientific/Engineering :: Physics
Provides-Extra: filter
Requires-Dist: numpy
Requires-Dist: openpyxl ; extra == "filter"
Requires-Dist: pandas
Requires-Dist: ruamel.yaml
Requires-Dist: scipy ; extra == "filter"
Requires-Dist: uproot ; extra == "filter"
Requires-Dist: validobj
Project-URL: Repository, https://github.com/NNPDF/nnpdf_data
